PdCom_Gateway-0.1.3.data/scripts/pdcom_gateway.py
pdcom_gateway_lib/__init__.py
pdcom_gateway_lib/config.py
pdcom_gateway_lib/modules/__init__.py
pdcom_gateway_lib/modules/NMEA/NMEA.py
pdcom_gateway_lib/modules/NMEA/__init__.py
PdCom_Gateway-0.1.3.dist-info/LICENSE
PdCom_Gateway-0.1.3.dist-info/METADATA
PdCom_Gateway-0.1.3.dist-info/WHEEL
PdCom_Gateway-0.1.3.dist-info/top_level.txt
PdCom_Gateway-0.1.3.dist-info/RECORD
