Metadata-Version: 2.1
Name: PdCom-Gateway
Version: 0.1.3
Summary: PdCom-Based Process Data Gateway
Home-page: UNKNOWN
Author: Bjarne von Horn
Author-email: vh@igh.de
License: UNKNOWN
Platform: UNKNOWN
Requires-Python: >=3.6
Requires-Dist: libconf
Requires-Dist: pdcom5 (>=5.3.0)
